odoo/addons/website_sale_product_detail_attribute_value_image/README.rst
odoo/addons/website_sale_product_detail_attribute_value_image/__init__.py
odoo/addons/website_sale_product_detail_attribute_value_image/__manifest__.py
odoo/addons/website_sale_product_detail_attribute_value_image/demo/assets_tour.xml
odoo/addons/website_sale_product_detail_attribute_value_image/i18n/ca.po
odoo/addons/website_sale_product_detail_attribute_value_image/i18n/es.po
odoo/addons/website_sale_product_detail_attribute_value_image/i18n/fr.po
odoo/addons/website_sale_product_detail_attribute_value_image/i18n/website_sale_product_detail_attribute_value_image.pot
odoo/addons/website_sale_product_detail_attribute_value_image/models/__init__.py
odoo/addons/website_sale_product_detail_attribute_value_image/models/product_attribute_value.py
odoo/addons/website_sale_product_detail_attribute_value_image/readme/CONTRIBUTORS.rst
odoo/addons/website_sale_product_detail_attribute_value_image/readme/CREDITS.rst
odoo/addons/website_sale_product_detail_attribute_value_image/readme/DESCRIPTION.rst
odoo/addons/website_sale_product_detail_attribute_value_image/readme/USAGE.rst
odoo/addons/website_sale_product_detail_attribute_value_image/static/description/icon.png
odoo/addons/website_sale_product_detail_attribute_value_image/static/description/index.html
odoo/addons/website_sale_product_detail_attribute_value_image/static/src/img/EN374.png
odoo/addons/website_sale_product_detail_attribute_value_image/static/src/img/EN374_2003.png
odoo/addons/website_sale_product_detail_attribute_value_image/static/src/img/EN388.png
odoo/addons/website_sale_product_detail_attribute_value_image/static/src/js/website_sale_product_detail_attribute_value_image_tour.js
odoo/addons/website_sale_product_detail_attribute_value_image/static/src/scss/style.scss
odoo/addons/website_sale_product_detail_attribute_value_image/templates/assets.xml
odoo/addons/website_sale_product_detail_attribute_value_image/templates/shop_product.xml
odoo13_addon_website_sale_product_detail_attribute_value_image-13.0.1.0.1.dev4.dist-info/METADATA
odoo13_addon_website_sale_product_detail_attribute_value_image-13.0.1.0.1.dev4.dist-info/WHEEL
odoo13_addon_website_sale_product_detail_attribute_value_image-13.0.1.0.1.dev4.dist-info/top_level.txt
odoo13_addon_website_sale_product_detail_attribute_value_image-13.0.1.0.1.dev4.dist-info/RECORD
